{
  "Workflows": [
    {
      "Path": null,
      "SortBy": 0,
      "VariablesSectionElementsOrder": [],
      "ArgumentsSectionElementsOrder": null,
      "ConstantsSectionElementsOrder": [],
      "AddedNamespaces": null
    },
    {
      "Path": "Main.xaml",
      "SortBy": 0,
      "VariablesSectionElementsOrder": [
        "sum&Sequence_1",
        "num2&Sequence_1",
        "num1&Sequence_1"
      ],
      "ArgumentsSectionElementsOrder": [
        "inSum",
        "outNum2",
        "outNum1"
      ],
      "ConstantsSectionElementsOrder": [],
      "AddedNamespaces": null
    },
    {
      "Path": "SumSequence.xaml",
      "SortBy": 0,
      "VariablesSectionElementsOrder": [],
      "ArgumentsSectionElementsOrder": [
        "outSum",
        "inNum2",
        "inNum1"
      ],
      "ConstantsSectionElementsOrder": [],
      "AddedNamespaces": null
    },
    {
      "Path": "SwapMain.xaml",
      "SortBy": 0,
      "VariablesSectionElementsOrder": [
        "temp&Sequence_1",
        "num2&Sequence_1",
        "num1&Sequence_1"
      ],
      "ArgumentsSectionElementsOrder": [],
      "ConstantsSectionElementsOrder": [],
      "AddedNamespaces": null
    }
  ]
}